{
  "count": 23,
  "items": [
    {
      "id": "1594c310d14dd224aad92f2923cda170",
      "title": "Mrbaeksang/deepcloak",
      "url": "https://github.com/Mrbaeksang/deepcloak",
      "source": "github",
      "source_author": "Mrbaeksang",
      "topics": [],
      "score": 6.5,
      "score_reason": "Low engagement but presents a novel project in AI.",
      "posted": false,
      "collected_at": "2026-06-05T04:58:23Z",
      "engagement": {
        "comments": 0,
        "likes": 0,
        "replies": 0,
        "retweets": 0,
        "stars": 23,
        "upvotes": 0
      }
    },
    {
      "id": "b34ca6fecdec63e0baddab8016b543e6",
      "title": "chaitanyagiri/munder-difflin",
      "url": "https://github.com/chaitanyagiri/munder-difflin",
      "source": "github",
      "source_author": "chaitanyagiri",
      "topics": [],
      "score": 6.5,
      "score_reason": "While interesting, the repository itself does not significantly change developer workflows.",
      "posted": false,
      "collected_at": "2026-06-05T04:58:14Z",
      "engagement": {
        "comments": 0,
        "likes": 0,
        "replies": 0,
        "retweets": 0,
        "stars": 208,
        "upvotes": 0
      }
    },
    {
      "id": "691b8d547526da3e55296583f05ccbf0",
      "title": "Xopoko/build-swift-apps",
      "url": "https://github.com/Xopoko/build-swift-apps",
      "source": "github",
      "source_author": "Xopoko",
      "topics": [],
      "score": 6.5,
      "score_reason": "Lack of engagement indicates lower relevance or novelty.",
      "posted": false,
      "collected_at": "2026-06-05T04:58:27Z",
      "engagement": {
        "comments": 0,
        "likes": 0,
        "replies": 0,
        "retweets": 0,
        "stars": 23,
        "upvotes": 0
      }
    },
    {
      "id": "69bea45f4e9d411fdd0a0b416a8d9c3b",
      "title": "PatrickSUDO/fadacai-portfolio",
      "url": "https://github.com/PatrickSUDO/fadacai-portfolio",
      "source": "github",
      "source_author": "PatrickSUDO",
      "topics": [],
      "score": 6.5,
      "score_reason": "Similar to others, it appears niche but has potential.",
      "posted": false,
      "collected_at": "2026-06-05T04:58:23Z",
      "engagement": {
        "comments": 0,
        "likes": 0,
        "replies": 0,
        "retweets": 0,
        "stars": 22,
        "upvotes": 0
      }
    },
    {
      "id": "3e042ce339423a17ef717152463ad01a",
      "title": "xszwow/Chrome2api",
      "url": "https://github.com/xszwow/Chrome2api",
      "source": "github",
      "source_author": "xszwow",
      "topics": [],
      "score": 6,
      "score_reason": "Automating API creation from Chrome could be useful but lacks broad application impact.",
      "posted": false,
      "collected_at": "2026-06-05T04:58:12Z",
      "engagement": {
        "comments": 0,
        "likes": 0,
        "replies": 0,
        "retweets": 0,
        "stars": 17,
        "upvotes": 0
      }
    },
    {
      "id": "92225cb499c704b6d7fdb519c5096c56",
      "title": "AtomFlow-AI/MoleCode",
      "url": "https://github.com/AtomFlow-AI/MoleCode",
      "source": "github",
      "source_author": "AtomFlow-AI",
      "topics": [],
      "score": 6,
      "score_reason": "Growing interest with some engagement, but still niche.",
      "posted": false,
      "collected_at": "2026-06-05T04:58:31Z",
      "engagement": {
        "comments": 0,
        "likes": 0,
        "replies": 0,
        "retweets": 0,
        "stars": 91,
        "upvotes": 0
      }
    },
    {
      "id": "7368172f0fe7870357c6379a9869027e",
      "title": "MSALab-PKU/LoomVideo",
      "url": "https://github.com/MSALab-PKU/LoomVideo",
      "source": "github",
      "source_author": "MSALab-PKU",
      "topics": [],
      "score": 5.5,
      "score_reason": "The repository may offer new capabilities, but relevance to current AI development trends is limited.",
      "posted": false,
      "collected_at": "2026-06-05T04:58:19Z",
      "engagement": {
        "comments": 0,
        "likes": 0,
        "replies": 0,
        "retweets": 0,
        "stars": 5,
        "upvotes": 0
      }
    },
    {
      "id": "9ab6407873818e095f7cbc6749b121ec",
      "title": "cliffbackerhope/AI-Audio-Content-Creator",
      "url": "https://github.com/cliffbackerhope/AI-Audio-Content-Creator",
      "source": "github",
      "source_author": "cliffbackerhope",
      "topics": [],
      "score": 5,
      "score_reason": "unscored",
      "posted": false,
      "collected_at": "2026-06-05T04:58:20Z",
      "engagement": {
        "comments": 0,
        "likes": 0,
        "replies": 0,
        "retweets": 0,
        "stars": 5,
        "upvotes": 0
      }
    },
    {
      "id": "13061323afdc0be8ffe97575e07c7eef",
      "title": "felipeluissalgueiro/hive",
      "url": "https://github.com/felipeluissalgueiro/hive",
      "source": "github",
      "source_author": "felipeluissalgueiro",
      "topics": [],
      "score": 5,
      "score_reason": "An open-source project but lacks engagement and demonstrable impact.",
      "posted": false,
      "collected_at": "2026-06-05T04:58:11Z",
      "engagement": {
        "comments": 0,
        "likes": 0,
        "replies": 0,
        "retweets": 0,
        "stars": 14,
        "upvotes": 0
      }
    },
    {
      "id": "e1dccb5560d3161128c15541df7d6198",
      "title": "CoalElderLobby/ai-detection-bypass-gptzero-turnitin",
      "url": "https://github.com/CoalElderLobby/ai-detection-bypass-gptzero-turnitin",
      "source": "github",
      "source_author": "CoalElderLobby",
      "topics": [],
      "score": 5,
      "score_reason": "unscored",
      "posted": false,
      "collected_at": "2026-06-05T04:58:13Z",
      "engagement": {
        "comments": 0,
        "likes": 0,
        "replies": 0,
        "retweets": 0,
        "stars": 17,
        "upvotes": 0
      }
    },
    {
      "id": "e948a6eb42243453e54f52ec9dbb609b",
      "title": "vinaygangidi/cash-application-foundry",
      "url": "https://github.com/vinaygangidi/cash-application-foundry",
      "source": "github",
      "source_author": "vinaygangidi",
      "topics": [],
      "score": 5,
      "score_reason": "unscored",
      "posted": false,
      "collected_at": "2026-06-05T04:58:22Z",
      "engagement": {
        "comments": 0,
        "likes": 0,
        "replies": 0,
        "retweets": 0,
        "stars": 1,
        "upvotes": 0
      }
    },
    {
      "id": "c7a3d82e2e7e0b6f9467c518da77e522",
      "title": "ntd4996/agentpet",
      "url": "https://github.com/ntd4996/agentpet",
      "source": "github",
      "source_author": "ntd4996",
      "topics": [],
      "score": 5,
      "score_reason": "unscored",
      "posted": false,
      "collected_at": "2026-06-05T04:58:32Z",
      "engagement": {
        "comments": 0,
        "likes": 0,
        "replies": 0,
        "retweets": 0,
        "stars": 66,
        "upvotes": 0
      }
    },
    {
      "id": "ce7cc4aba4e322317b3eebc6f30c44c5",
      "title": "sc4rfurry/KimiK0",
      "url": "https://github.com/sc4rfurry/KimiK0",
      "source": "github",
      "source_author": "sc4rfurry",
      "topics": [],
      "score": 5,
      "score_reason": "unscored",
      "posted": false,
      "collected_at": "2026-06-05T04:58:18Z",
      "engagement": {
        "comments": 0,
        "likes": 0,
        "replies": 0,
        "retweets": 0,
        "stars": 1,
        "upvotes": 0
      }
    },
    {
      "id": "1f4981e479652512e8167ef13b8c866d",
      "title": "rextanka/zero-cost-cline",
      "url": "https://github.com/rextanka/zero-cost-cline",
      "source": "github",
      "source_author": "rextanka",
      "topics": [],
      "score": 5,
      "score_reason": "unscored",
      "posted": false,
      "collected_at": "2026-06-05T04:58:32Z",
      "engagement": {
        "comments": 0,
        "likes": 0,
        "replies": 0,
        "retweets": 0,
        "stars": 57,
        "upvotes": 0
      }
    },
    {
      "id": "bafb359358d2fba67624cd46e2eefc90",
      "title": "Unitbruattract/Lossless-Scaling-Download-2026",
      "url": "https://github.com/Unitbruattract/Lossless-Scaling-Download-2026",
      "source": "github",
      "source_author": "Unitbruattract",
      "topics": [],
      "score": 5,
      "score_reason": "unscored",
      "posted": false,
      "collected_at": "2026-06-05T04:58:19Z",
      "engagement": {
        "comments": 0,
        "likes": 0,
        "replies": 0,
        "retweets": 0,
        "stars": 137,
        "upvotes": 0
      }
    },
    {
      "id": "6ed1d751b19307fa6a09705beee1537d",
      "title": "enderzcx/pi-docs-playbook",
      "url": "https://github.com/enderzcx/pi-docs-playbook",
      "source": "github",
      "source_author": "enderzcx",
      "topics": [],
      "score": 4.5,
      "score_reason": "Documentation playbooks are useful but less novel for a typical developer audience.",
      "posted": false,
      "collected_at": "2026-06-05T04:58:14Z",
      "engagement": {
        "comments": 0,
        "likes": 0,
        "replies": 0,
        "retweets": 0,
        "stars": 114,
        "upvotes": 0
      }
    },
    {
      "id": "edb81f9739ea1c4a25ace23354df9f69",
      "title": "myccarl/ai-shortVideo-pipeline",
      "url": "https://github.com/myccarl/ai-shortVideo-pipeline",
      "source": "github",
      "source_author": "myccarl",
      "topics": [],
      "score": 4,
      "score_reason": "While addressing AI detection, it does not present substantial novelty or impact.",
      "posted": false,
      "collected_at": "2026-06-05T04:58:15Z",
      "engagement": {
        "comments": 0,
        "likes": 0,
        "replies": 0,
        "retweets": 0,
        "stars": 14,
        "upvotes": 0
      }
    },
    {
      "id": "9d2a00fe297bbfee86295c7de4a4a40b",
      "title": "NJU-Speech/Foley-Omni",
      "url": "https://github.com/NJU-Speech/Foley-Omni",
      "source": "github",
      "source_author": "NJU-Speech",
      "topics": [],
      "score": 3.5,
      "score_reason": "Audio content tools are emerging but the repository shows minimal engagement signals.",
      "posted": false,
      "collected_at": "2026-06-05T04:58:19Z",
      "engagement": {
        "comments": 0,
        "likes": 0,
        "replies": 0,
        "retweets": 0,
        "stars": 6,
        "upvotes": 0
      }
    },
    {
      "id": "8c5342591c6c2c3bd3216eea5eb64683",
      "title": "Moh4696/50-essential-mcp-servers",
      "url": "https://github.com/Moh4696/50-essential-mcp-servers",
      "source": "github",
      "source_author": "Moh4696",
      "topics": [],
      "score": 3,
      "score_reason": "The repository has limited potential and engagement, making it less appealing.",
      "posted": false,
      "collected_at": "2026-06-05T04:58:23Z",
      "engagement": {
        "comments": 0,
        "likes": 0,
        "replies": 0,
        "retweets": 0,
        "stars": 25,
        "upvotes": 0
      }
    },
    {
      "id": "3f08be7158ee46106fe3bdc7be6b99fa",
      "title": "zzj2004/kimi-vision",
      "url": "https://github.com/zzj2004/kimi-vision",
      "source": "github",
      "source_author": "zzj2004",
      "topics": [],
      "score": 2.5,
      "score_reason": "Low engagement and minimal innovation suggest it is less of interest to developers.",
      "posted": false,
      "collected_at": "2026-06-05T04:58:18Z",
      "engagement": {
        "comments": 0,
        "likes": 0,
        "replies": 0,
        "retweets": 0,
        "stars": 1,
        "upvotes": 0
      }
    },
    {
      "id": "6a25d1c3abce337a0720ce5718e121a7",
      "title": "HopeKeeperEmpty/cc-fleet-315",
      "url": "https://github.com/HopeKeeperEmpty/cc-fleet-315",
      "source": "github",
      "source_author": "HopeKeeperEmpty",
      "topics": [],
      "score": 2,
      "score_reason": "Very low engagement, and the purpose is unclear.",
      "posted": false,
      "collected_at": "2026-06-05T04:58:18Z",
      "engagement": {
        "comments": 0,
        "likes": 0,
        "replies": 0,
        "retweets": 0,
        "stars": 5,
        "upvotes": 0
      }
    },
    {
      "id": "207e7ff9e39d3a8e8a617f8734f7aceb",
      "title": "polyhook/polyhook",
      "url": "https://github.com/polyhook/polyhook",
      "source": "github",
      "source_author": "polyhook",
      "topics": [],
      "score": 1.5,
      "score_reason": "Extremely low engagement with little relevance.",
      "posted": false,
      "collected_at": "2026-06-05T04:58:28Z",
      "engagement": {
        "comments": 0,
        "likes": 0,
        "replies": 0,
        "retweets": 0,
        "stars": 2,
        "upvotes": 0
      }
    },
    {
      "id": "ef9b59b13b4267eecbbdbc9133baf9cb",
      "title": "kelescxs/devin",
      "url": "https://github.com/kelescxs/devin",
      "source": "github",
      "source_author": "kelescxs",
      "topics": [],
      "score": 1,
      "score_reason": "Obscure project with no engagement or relevance.",
      "posted": false,
      "collected_at": "2026-06-05T04:58:29Z",
      "engagement": {
        "comments": 0,
        "likes": 0,
        "replies": 0,
        "retweets": 0,
        "stars": 0,
        "upvotes": 0
      }
    }
  ],
  "source": "github",
  "updated_at": "2026-06-05T05:02:28Z"
}